baking/__init__.py
baking/import.py
baking/naturalize.py
baking_wijesooriya-1.1.8.dist-info/LICENSE
baking_wijesooriya-1.1.8.dist-info/METADATA
baking_wijesooriya-1.1.8.dist-info/WHEEL
baking_wijesooriya-1.1.8.dist-info/top_level.txt
baking_wijesooriya-1.1.8.dist-info/RECORD
