Metadata-Version: 2.1
Name: baking-wijesooriya
Version: 1.1.8
Summary: Contains functions named after the steps of baking to help with cake baking analogy for beginners.
Home-page: https://github.com/pypa/sampleproject
Author: Kiran Wijesooriya
Author-email: kiranw1000@gmail.com
License: UNKNOWN
Platform: UNKNOWN
Classifier: Programming Language :: Python :: 3
Classifier: License :: OSI Approved :: MIT License
Classifier: Operating System :: OS Independent
Requires-Python: >=3.6
